pdf_manipulation/__init__.py
pdf_manipulation-0.0.2.dist-info/METADATA
pdf_manipulation-0.0.2.dist-info/WHEEL
pdf_manipulation-0.0.2.dist-info/licenses/LICENSE
pdf_manipulation-0.0.2.dist-info/RECORD
